code_kernel/__init__.py
code_kernel/begin_evaluation.py
code_kernel_config/__init__.py
code_kernel_config/supported_languages.py
code_kernel_exceptions/CodeKernelException.py
code_kernel_exceptions/CodeTimeoutError.py
code_kernel_exceptions/CompilationError.py
code_kernel_exceptions/ExecutionError.py
code_kernel_exceptions/FailedProcessError.py
code_kernel_exceptions/MissingOutputsError.py
code_kernel_exceptions/UnsupportedLanguageError.py
code_kernel_exceptions/__init__.py
code_kernel_exercise/__init__.py
code_kernel_exercise/run_exercise.py
code_kernel_file_handling/__init__.py
code_kernel_file_handling/create_temp_file.py
code_kernel_file_handling/delete_temp_file.py
code_kernel_runners/__init__.py
code_kernel_runners/cpp_runner.py
code_kernel_runners/py_runner.py
code_kernel_utils/__init__.py
code_kernel_utils/language_utils.py
code_kernel_utils/os_utils.py
code_kernel_utils/process_utils.py
Code_Evaluator_Kernel-1.0.0a0.dist-info/LICENSE.txt
Code_Evaluator_Kernel-1.0.0a0.dist-info/METADATA
Code_Evaluator_Kernel-1.0.0a0.dist-info/WHEEL
Code_Evaluator_Kernel-1.0.0a0.dist-info/top_level.txt
Code_Evaluator_Kernel-1.0.0a0.dist-info/RECORD
