Metadata-Version: 2.1
Name: Code-Evaluator-Kernel
Version: 1.0.0a0
Summary: A library for black box testing code. Ideal for evaluate students code
Home-page: https://github.com/pypa/sampleproject
Author: MarceloDeJesusNunez
Author-email: mdjnunez9706@gmail.com
Project-URL: Bug Tracker, https://github.com/pypa/sampleproject/issues
Classifier: Programming Language :: Python :: 3
Classifier: Operating System :: OS Independent
Requires-Python: >=3.6
License-File: LICENSE.txt
